ucluster/__init__.py
ucluster/text_cluster.py
ucluster/vd/__init__.py
ucluster/vd/plugin.py
ucluster-0.3.2.dist-info/WHEEL
ucluster-0.3.2.dist-info/METADATA
ucluster-0.3.2.dist-info/RECORD
