Metadata-Version: 2.1
Name: ucluster
Version: 0.3.2
Summary: Text-based clustering utility
Author: R. Miles McCain
Author-email: github@sendmiles.email
Requires-Python: >=3.8,<4.0
Classifier: Programming Language :: Python :: 3
Classifier: Programming Language :: Python :: 3.10
Classifier: Programming Language :: Python :: 3.8
Classifier: Programming Language :: Python :: 3.9
Requires-Dist: fasttext (>=0.9.2,<0.10.0)
Requires-Dist: hdbscan (>=0.8.29,<0.9.0)
Requires-Dist: loguru (>=0.6.0,<0.7.0)
Requires-Dist: nltk (>=3.7,<4.0)
Requires-Dist: visidata (>=2.10,<3.0)
